odoo9_addon_account_check_deposit-9.0.0.1.0-py2.7-nspkg.pth
odoo9_addon_account_check_deposit-9.0.0.1.0.dist-info/DESCRIPTION.rst
odoo9_addon_account_check_deposit-9.0.0.1.0.dist-info/METADATA
odoo9_addon_account_check_deposit-9.0.0.1.0.dist-info/RECORD
odoo9_addon_account_check_deposit-9.0.0.1.0.dist-info/WHEEL
odoo9_addon_account_check_deposit-9.0.0.1.0.dist-info/metadata.json
odoo9_addon_account_check_deposit-9.0.0.1.0.dist-info/namespace_packages.txt
odoo9_addon_account_check_deposit-9.0.0.1.0.dist-info/top_level.txt
odoo_addons/account_check_deposit/README.rst
odoo_addons/account_check_deposit/__init__.py
odoo_addons/account_check_deposit/__openerp__.py
odoo_addons/account_check_deposit/data/account_data.xml
odoo_addons/account_check_deposit/data/account_deposit_sequence.xml
odoo_addons/account_check_deposit/i18n/account_check_deposit.pot
odoo_addons/account_check_deposit/i18n/am.po
odoo_addons/account_check_deposit/i18n/ar.po
odoo_addons/account_check_deposit/i18n/bs.po
odoo_addons/account_check_deposit/i18n/ca.po
odoo_addons/account_check_deposit/i18n/ca_ES.po
odoo_addons/account_check_deposit/i18n/cs.po
odoo_addons/account_check_deposit/i18n/de.po
odoo_addons/account_check_deposit/i18n/el_GR.po
odoo_addons/account_check_deposit/i18n/en_GB.po
odoo_addons/account_check_deposit/i18n/es.po
odoo_addons/account_check_deposit/i18n/es_CR.po
odoo_addons/account_check_deposit/i18n/es_EC.po
odoo_addons/account_check_deposit/i18n/es_ES.po
odoo_addons/account_check_deposit/i18n/es_MX.po
odoo_addons/account_check_deposit/i18n/es_VE.po
odoo_addons/account_check_deposit/i18n/et.po
odoo_addons/account_check_deposit/i18n/fi.po
odoo_addons/account_check_deposit/i18n/fr.po
odoo_addons/account_check_deposit/i18n/gl.po
odoo_addons/account_check_deposit/i18n/gl_ES.po
odoo_addons/account_check_deposit/i18n/gu.po
odoo_addons/account_check_deposit/i18n/hr.po
odoo_addons/account_check_deposit/i18n/hr_HR.po
odoo_addons/account_check_deposit/i18n/hu.po
odoo_addons/account_check_deposit/i18n/id.po
odoo_addons/account_check_deposit/i18n/it.po
odoo_addons/account_check_deposit/i18n/ja.po
odoo_addons/account_check_deposit/i18n/lt.po
odoo_addons/account_check_deposit/i18n/mk.po
odoo_addons/account_check_deposit/i18n/mn.po
odoo_addons/account_check_deposit/i18n/nb.po
odoo_addons/account_check_deposit/i18n/nl.po
odoo_addons/account_check_deposit/i18n/nl_BE.po
odoo_addons/account_check_deposit/i18n/pl.po
